rptf/__init__.py
rptf/api.py
rptf/rptf.py
rptf/schema.py
rptf/term.py
rptf-0.1.12.dist-info/METADATA
rptf-0.1.12.dist-info/WHEEL
rptf-0.1.12.dist-info/entry_points.txt
rptf-0.1.12.dist-info/top_level.txt
rptf-0.1.12.dist-info/RECORD
