Metadata-Version: 2.1
Name: rptf
Version: 0.1.12
Summary: End-to-end pipeline test framework for GitLab
Home-page: https://gitlab.com/sri-at-gitlab/projects/remote-pipeline-test-framework/framework
Author: Sri
Author-email: hello@srirangan.net
License: UNKNOWN
Platform: UNKNOWN
Classifier: Programming Language :: Python :: 3
Classifier: License :: OSI Approved :: MIT License
Classifier: Operating System :: OS Independent
Requires-Python: >=3.6
Requires-Dist: cerberus (==1.3.2)
Requires-Dist: click (==7.1.2)
Requires-Dist: colorama (==0.4.4)
Requires-Dist: requests (==2.25.1)
Requires-Dist: pyyaml (==5.3.1)
Requires-Dist: junitparser (==1.6.3)
